ipatok/__init__.py
ipatok/ipa.py
ipatok/tokens.py
ipatok/data/ipa_2015.tsv
ipatok/data/replacements.tsv
ipatok/tests/__init__.py
ipatok/tests/test_ipa.py
ipatok/tests/test_tokens.py
ipatok-0.4.2.dist-info/LICENSE
ipatok-0.4.2.dist-info/WHEEL
ipatok-0.4.2.dist-info/METADATA
ipatok-0.4.2.dist-info/RECORD
