Metadata-Version: 2.1
Name: ipatok
Version: 0.4.2
Summary: IPA tokeniser
Keywords: IPA,tokeniser,tokenizer
Author-email: pavelsof <mail@pavelsof.com>
Classifier: Development Status :: 4 - Beta
Classifier: Intended Audience :: Science/Research
Classifier: License :: OSI Approved :: MIT License
Classifier: Programming Language :: Python :: 3
Classifier: Topic :: Text Processing :: Linguistic
Project-URL: Changelog, https://github.com/pavelsof/ipatok/blob/master/CHANGELOG.rst
Project-URL: Home, https://github.com/pavelsof/ipatok
Project-URL: Source, https://github.com/pavelsof/ipatok
Project-URL: Tracker, https://github.com/pavelsof/ipatok/issues
